bacpypes/__init__.py
bacpypes/analysis.py
bacpypes/apdu.py
bacpypes/app.py
bacpypes/appservice.py
bacpypes/basetypes.py
bacpypes/bsll.py
bacpypes/bsllservice.py
bacpypes/bvll.py
bacpypes/bvllservice.py
bacpypes/capability.py
bacpypes/comm.py
bacpypes/commandlogging.py
bacpypes/console.py
bacpypes/consolecmd.py
bacpypes/consolelogging.py
bacpypes/constructeddata.py
bacpypes/core.py
bacpypes/debugging.py
bacpypes/errors.py
bacpypes/event.py
bacpypes/iocb.py
bacpypes/netservice.py
bacpypes/npdu.py
bacpypes/object.py
bacpypes/pdu.py
bacpypes/primitivedata.py
bacpypes/settings.py
bacpypes/singleton.py
bacpypes/task.py
bacpypes/tcp.py
bacpypes/udp.py
bacpypes/vlan.py
bacpypes/local/__init__.py
bacpypes/local/device.py
bacpypes/local/file.py
bacpypes/local/object.py
bacpypes/local/schedule.py
bacpypes/service/__init__.py
bacpypes/service/cov.py
bacpypes/service/detect.py
bacpypes/service/device.py
bacpypes/service/file.py
bacpypes/service/object.py
bacpypes/service/test.py
bacpypes-0.18.7.dist-info/DESCRIPTION.rst
bacpypes-0.18.7.dist-info/METADATA
bacpypes-0.18.7.dist-info/RECORD
bacpypes-0.18.7.dist-info/WHEEL
bacpypes-0.18.7.dist-info/metadata.json
bacpypes-0.18.7.dist-info/top_level.txt
